CHANGELOG.md
neptune_prophet/__init__.py
neptune_prophet/impl/__init__.py
neptune_prophet/impl/version.py
neptune_prophet-1.0.2.dist-info/LICENSE
neptune_prophet-1.0.2.dist-info/METADATA
neptune_prophet-1.0.2.dist-info/WHEEL
neptune_prophet-1.0.2.dist-info/RECORD
